pdf_extractor/__init__.py
pdf_extractor/cleaning_encoding.py
pdf_extractor/date_miner.py
pdf_extractor/pdf_extractor.py
pdf_extractor/text_extraction.py
pdf_extractor/text_summarizer.py
extracteur_de_fou_malade_pour_charles_le_charlo-0.0.1.dist-info/LICENSE
extracteur_de_fou_malade_pour_charles_le_charlo-0.0.1.dist-info/METADATA
extracteur_de_fou_malade_pour_charles_le_charlo-0.0.1.dist-info/WHEEL
extracteur_de_fou_malade_pour_charles_le_charlo-0.0.1.dist-info/top_level.txt
extracteur_de_fou_malade_pour_charles_le_charlo-0.0.1.dist-info/RECORD
