Metadata-Version: 2.1
Name: extracteur-de-fou-malade-pour-charles-le-charlo
Version: 0.0.1
Summary: PDF data parser
Home-page: UNKNOWN
Author: Jordan
Author-email: hehe@example.com
License: UNKNOWN
Platform: UNKNOWN
Classifier: Programming Language :: Python :: 3
Classifier: License :: OSI Approved :: MIT License
Classifier: Operating System :: OS Independent
Requires-Python: >=3.7
Requires-Dist: textract (>=1.6.3)
Requires-Dist: bbcode (>=1.0.33)
Requires-Dist: pdfminer3 (>=2018.12.3.0)
Requires-Dist: ftfy (>=5.5.1)
Requires-Dist: langid (>=1.1.6)
Requires-Dist: sumy (>=0.8.1)
